setup.py
DecisionTreeBktUtil/__init__.py
DecisionTreeBktUtil/bkt_utils.py
DecisionTreeBktUtil/getColBktFromDF.py
DecisionTreeBktUtil/main.py
DecisionTreeBktUtil.egg-info/PKG-INFO
DecisionTreeBktUtil.egg-info/SOURCES.txt
DecisionTreeBktUtil.egg-info/dependency_links.txt
DecisionTreeBktUtil.egg-info/top_level.txt