Metadata-Version: 2.1
Name: DecisionTreeBktUtil
Version: 2.1.3
Summary: toad包来进行分桶。
Home-page: https://github.com/HeiBoWang/DecisionTreeBktUtil
Author: wangyongpeng
Author-email: wangyongpeng@zhuanzhuan.com
License: BSD Licence
Keywords: pip,wangyongpeng,tree
Platform: any
